{
    "si_units": ["l", "m", "t", "q"],
    "units": [
        {"name": "l", "coeffs": [1, 0, 0, 0]},
        {"name": "m", "coeffs": [0, 1, 0, 0]},
        {"name": "t", "coeffs": [0, 0, 1, 0]},
        {"name": "q", "coeffs": [0, 0, 0, 1]},
        {"name": "p", "coeffs": [1, 1, -1, 0]},
        {"name": "v", "coeffs": [1, 0, -1, 0]},
        {"name": "h", "coeffs": [2, 1, -1, 0]},
        {"name": "G", "coeffs": [3, -1, -2, 0]},
        {"name": "epsilon", "coeffs": [-3, -1, 2, 2]},
        {"name": "mu", "coeffs": [1, 1, 0, -2]},
        {"name": "Z", "coeffs": [2, 1, -1, -2]}
    ]
}
